{
  "Age": 85,
  "Gender": 0,
  "Ethnicity": 1,
  "EducationLevel": 0,
  "BMI": 35.1,
  "Smoking": 1,
  "AlcoholConsumption": 21.7,
  "PhysicalActivity": 1.2,
  "DietQuality": 1.8,
  "SleepQuality": 3.2,
  "FamilyHistoryAlzheimers": 1,
  "CardiovascularDisease": 1,
  "Diabetes": 1,
  "Depression": 1,
  "HeadInjury": 1,
  "Hypertension": 1,
  "SystolicBP": 175,
  "DiastolicBP": 100,
  "CholesterolTotal": 299.9,
  "CholesterolLDL": 210.4,
  "CholesterolHDL": 32.9,
  "CholesterolTriglycerides": 342.8,
  "MMSE": 3.5,
  "FunctionalAssessment": 2.1,
  "MemoryComplaints": 1,
  "BehavioralProblems": 1,
  "ADL": 9.8,
  "Confusion": 1,
  "Disorientation": 1,
  "PersonalityChanges": 1,
  "DifficultyCompletingTasks": 1,
  "Forgetfulness": 1
}
